{
    "id": 5825,
    "name": "adult lymphoma",
    "source": "DOID",
    "definition": null,
    "currentPreferredTerm": null,
    "lastUpdateDateFromDO": "03/24/2020",
    "altIds": [
        
    ],
    "termId": "DOID:5825",
    "evidence": [
        
    ],
    "clinicalTrials": [
        {
            "nctId": "NCT02214147",
            "title": "Pharmacokinetics of Alisertib in Adults With Advanced Solid Tumors or Relapsed/Refractory Lymphoma With Varying Degrees of Hepatic Function",
            "phase": "Phase I",
            "recruitment": "Completed",
            "therapies": [
                {
                    "id": 626,
                    "therapyName": "Alisertib",
                    "synonyms": null
                }
            ]
        }
    ]
}