{
    "id": 50610,
    "name": "oral cavity carcinoma in situ",
    "source": "DOID",
    "definition": "An in situ carcinoma of the oral cavity that is located_in the epithelium. It is the most common cause of leukoplakia and associated with the development of squamous cell carcinoma. [url:https\\://www.dermnetnz.org/topics/carcinoma-in-situ-of-oral-cavity/]",
    "currentPreferredTerm": null,
    "lastUpdateDateFromDO": "03/24/2020",
    "altIds": [
        
    ],
    "termId": "DOID:0050610",
    "evidence": [
        
    ],
    "clinicalTrials": [
        {
            "nctId": "NCT02882282",
            "title": "Study of Pembrolizumab (MK-3475) for High Risk Oral Intra-Epithelial Neoplasias",
            "phase": "Phase II",
            "recruitment": "Active, not recruiting",
            "therapies": [
                {
                    "id": 1447,
                    "therapyName": "Pembrolizumab",
                    "synonyms": null
                }
            ]
        }
    ]
}