{
    "id": 3873,
    "name": "nodular medulloblastoma",
    "source": "DOID",
    "definition": null,
    "currentPreferredTerm": null,
    "lastUpdateDateFromDO": "03/24/2020",
    "altIds": [
        
    ],
    "termId": "DOID:3873",
    "evidence": [
        
    ],
    "clinicalTrials": [
        {
            "nctId": "NCT02017964",
            "title": "Combination Chemotherapy in Treating Younger Patients With Newly Diagnosed, Non-Metastatic Desmoplastic Medulloblastoma",
            "phase": "Phase II",
            "recruitment": "Active, not recruiting",
            "therapies": [
                {
                    "id": 1791,
                    "therapyName": "Carboplatin + Etoposide",
                    "synonyms": null
                },
                {
                    "id": 2673,
                    "therapyName": "Cyclophosphamide + Methotrexate + Vincristine",
                    "synonyms": null
                }
            ]
        }
    ]
}